{"m_key":"play_zuduililian","m_curSelectLogic":"room","m_startLevelLogic":"room","m_levelLogicList":[{"m_name":"room","m_scene":"Level_Huzhongzhenyao","m_sceneStyle":"","m_levelBornList":[{"m_bornId":"1","m_pos":{"x":0.03001437894999981,"y":-2.0216875076293947,"z":-11.540772438049317},"m_dir":{"x":0.0,"y":0.0,"z":0.0}},{"m_bornId":"2","m_pos":{"x":-2.9602015018463136,"y":-2.0142621994018556,"z":-12.610810279846192},"m_dir":{"x":0.0,"y":0.0,"z":0.0}},{"m_bornId":"3","m_pos":{"x":2.6200993061065676,"y":-2.0169382095336916,"z":-12.290620803833008},"m_dir":{"x":0.0,"y":0.0,"z":0.0}},{"m_bornId":"4","m_pos":{"x":1.870117425918579,"y":-2.0013628005981447,"z":-15.200952529907227},"m_dir":{"x":0.0,"y":0.0,"z":0.0}},{"m_bornId":"5","m_pos":{"x":-1.9600942134857178,"y":-1.9992237091064454,"z":-15.570907592773438},"m_dir":{"x":0.0,"y":0.0,"z":0.0}}],"m_levelSpawnList":[{"m_spawnId":"boss1","m_spawnGroupId":"","m_name":"","m_isRandomSpawn":false,"m_lookToPlayer":false,"m_isToGround":true,"m_isPassivity":false,"m_fieldOfVision":-1.0,"m_shareView":false,"m_startNum":1,"m_startCd":0.0,"m_maxNum":1,"m_survivalLimit":-1,"m_spawnType":0,"m_spawnParam1":0.0,"m_spawnParam2":0,"m_spawnParam3":0,"m_patrolId":"","m_bornAction":"","m_enterBattleAction":"","m_defaultIdle":"","m_bornBubb":"","m_enterBattleBubb":"","m_enterBattleSigh":false,"m_randomIdle":"","m_autoPatrol":"","m_objs":[3024],"m_names":["1"],"m_postions":[{"x":0.030000008642673494,"y":-2.0438647270202638,"z":0.009999056346714497}],"m_dirs":[{"x":0.0,"y":180.0,"z":0.0}],"m_scales":[{"x":1.0,"y":1.0,"z":1.0}]},{"m_spawnId":"lubiao","m_spawnGroupId":"","m_name":"","m_isRandomSpawn":false,"m_lookToPlayer":false,"m_isToGround":true,"m_isPassivity":false,"m_fieldOfVision":-1.0,"m_shareView":false,"m_startNum":12,"m_startCd":0.0,"m_maxNum":12,"m_survivalLimit":-1,"m_spawnType":0,"m_spawnParam1":0.0,"m_spawnParam2":0,"m_spawnParam3":0,"m_patrolId":"","m_bornAction":"","m_enterBattleAction":"","m_defaultIdle":"","m_bornBubb":"","m_enterBattleBubb":"","m_enterBattleSigh":false,"m_randomIdle":"","m_autoPatrol":"","m_objs":[32020],"m_names":["12","11","10","9","8","7","6","5","4","3","2","1"],"m_postions":[{"x":7.060117244720459,"y":-2.038762092590332,"z":4.300052165985107},{"x":2.680039405822754,"y":-2.040656566619873,"z":7.450034141540527},{"x":-2.220036029815674,"y":-2.0404462814331056,"z":7.760092258453369},{"x":-6.360170364379883,"y":-2.039130687713623,"z":5.2674174308776859},{"x":-8.030220031738282,"y":-2.0408835411071779,"z":-0.3000544309616089},{"x":-7.160120487213135,"y":-2.0392203330993654,"z":-4.3201117515563969},{"x":-4.000068664550781,"y":-2.0403614044189455,"z":-7.130199432373047},{"x":0.14999602735042573,"y":-2.038811683654785,"z":-8.420165061950684},{"x":4.210002422332764,"y":-2.039066791534424,"z":-7.220130920410156},{"x":6.980136394500732,"y":-2.039630889892578,"z":-4.260112285614014},{"x":8.3001708984375,"y":-2.038559913635254,"z":-0.11001087725162506},{"x":7.060117244720459,"y":-2.038762092590332,"z":4.300052165985107}],"m_dirs":[{"x":0.0,"y":0.0,"z":0.0},{"x":0.0,"y":0.0,"z":0.0},{"x":0.0,"y":0.0,"z":0.0},{"x":0.0,"y":0.0,"z":0.0},{"x":0.0,"y":0.0,"z":0.0},{"x":0.0,"y":0.0,"z":0.0},{"x":0.0,"y":0.0,"z":0.0},{"x":0.0,"y":0.0,"z":0.0},{"x":0.0,"y":0.0,"z":0.0},{"x":0.0,"y":0.0,"z":0.0},{"x":0.0,"y":0.0,"z":0.0},{"x":0.0,"y":0.0,"z":0.0}],"m_scales":[{"x":1.0,"y":1.0,"z":1.0},{"x":1.0,"y":1.0,"z":1.0},{"x":1.0,"y":1.0,"z":1.0},{"x":1.0,"y":1.0,"z":1.0},{"x":1.0,"y":1.0,"z":1.0},{"x":1.0,"y":1.0,"z":1.0},{"x":1.0,"y":1.0,"z":1.0},{"x":1.0,"y":1.0,"z":1.0},{"x":1.0,"y":1.0,"z":1.0},{"x":1.0,"y":1.0,"z":1.0},{"x":1.0,"y":1.0,"z":1.0},{"x":1.0,"y":1.0,"z":1.0}]},{"m_spawnId":"NPC1","m_spawnGroupId":"","m_name":"","m_isRandomSpawn":false,"m_lookToPlayer":false,"m_isToGround":true,"m_isPassivity":false,"m_fieldOfVision":-1.0,"m_shareView":false,"m_startNum":1,"m_startCd":0.0,"m_maxNum":1,"m_survivalLimit":-1,"m_spawnType":0,"m_spawnParam1":0.0,"m_spawnParam2":0,"m_spawnParam3":0,"m_patrolId":"","m_bornAction":"","m_enterBattleAction":"","m_defaultIdle":"","m_bornBubb":"","m_enterBattleBubb":"","m_enterBattleSigh":false,"m_randomIdle":"","m_autoPatrol":"","m_objs":[31013],"m_names":["1"],"m_postions":[{"x":7.0601091384887699,"y":-2.038762092590332,"z":4.300048828125}],"m_dirs":[{"x":0.0,"y":0.0,"z":0.0}],"m_scales":[{"x":1.0,"y":1.0,"z":1.0}]}],"m_levelPointList":[{"m_pointSetId":"path","m_postions":[{"x":-9.500240325927735,"y":-2.030369758605957,"z":-3.2001054286956789}],"m_dirs":[{"x":0.0,"y":270.0,"z":0.0}],"m_names":["1"],"m_saveToGround":true}],"m_levelPathList":[{"m_pathId":"path1","m_speed":1.0,"m_postions":[{"x":7.060117244720459,"y":-2.038762092590332,"z":4.300052165985107},{"x":8.3001708984375,"y":-2.038559913635254,"z":-0.11001087725162506},{"x":6.980136394500732,"y":-2.039630889892578,"z":-4.260112285614014},{"x":4.210002422332764,"y":-2.039066791534424,"z":-7.220130920410156},{"x":0.14999602735042573,"y":-2.038811683654785,"z":-8.420165061950684},{"x":-4.000068664550781,"y":-2.0403614044189455,"z":-7.130199432373047},{"x":-7.160120487213135,"y":-2.0392203330993654,"z":-4.3201117515563969},{"x":-8.030220031738282,"y":-2.0408835411071779,"z":-0.3000544309616089},{"x":-6.360170364379883,"y":-2.039130687713623,"z":5.2674174308776859},{"x":-2.220036029815674,"y":-2.0404462814331056,"z":7.760092258453369},{"x":2.680039405822754,"y":-2.040656566619873,"z":7.450034141540527},{"x":7.060117244720459,"y":-2.038762092590332,"z":4.300052165985107}],"m_dirs":[{"x":0.0,"y":0.0,"z":0.0},{"x":0.0,"y":0.0,"z":0.0},{"x":0.0,"y":0.0,"z":0.0},{"x":0.0,"y":0.0,"z":0.0},{"x":0.0,"y":0.0,"z":0.0},{"x":0.0,"y":0.0,"z":0.0},{"x":0.0,"y":0.0,"z":0.0},{"x":0.0,"y":0.0,"z":0.0},{"x":0.0,"y":0.0,"z":0.0},{"x":0.0,"y":0.0,"z":0.0},{"x":0.0,"y":0.0,"z":0.0},{"x":0.0,"y":0.0,"z":0.0}],"m_names":["1","2","3","4","5","6","7","8","9","10","11","12"],"m_stayTimes":[0.0,10.0,10.0,0.0,10.0,10.0,0.0,10.0,10.0,0.0,10.0,10.0],"m_speeds":[1.0,2.0,3.0,1.0,2.0,3.0,1.0,2.0,3.0,1.0,2.0,3.0],"m_events":["path1p1","path1p2","path1p3","path1p1","path1p2","path1p3","path1p1","path1p2","path1p3","path1p1","path1p2","path1p3"],"m_saveToGround":true}],"m_levelAreaList":[],"m_roomEventList":[{"m_eventId":"battle1","m_conditions":[{"m_conditionType":4,"m_isOr":false,"m_param1":"0","m_param2":"","m_param3":"","m_param4":"","m_param5":""}],"m_actions":[{"m_actionType":200,"m_delay":0.0,"m_param1":"lubiao","m_param2":"","m_param3":"","m_param4":"","m_param5":""},{"m_actionType":200,"m_delay":0.0,"m_param1":"NPC1","m_param2":"","m_param3":"","m_param4":"","m_param5":""},{"m_actionType":31000,"m_delay":0.5,"m_param1":"NPC1","m_param2":"path1","m_param3":"True","m_param4":"","m_param5":""}],"m_showMonitor":true},{"m_eventId":"path1p1","m_conditions":[{"m_conditionType":0,"m_isOr":false,"m_param1":"0","m_param2":"","m_param3":"","m_param4":"","m_param5":""}],"m_actions":[{"m_actionType":31400,"m_delay":0.0,"m_param1":"NPC1","m_param2":"271","m_param3":"4","m_param4":"","m_param5":""}],"m_showMonitor":true},{"m_eventId":"path1p2","m_conditions":[{"m_conditionType":0,"m_isOr":false,"m_param1":"0","m_param2":"","m_param3":"","m_param4":"","m_param5":""}],"m_actions":[{"m_actionType":31200,"m_delay":0.0,"m_param1":"NPC1","m_param2":"2","m_param3":"-2","m_param4":"15","m_param5":""},{"m_actionType":31400,"m_delay":0.0,"m_param1":"NPC1","m_param2":"372","m_param3":"4","m_param4":"","m_param5":""}],"m_showMonitor":true},{"m_eventId":"path1p3","m_conditions":[{"m_conditionType":0,"m_isOr":false,"m_param1":"0","m_param2":"","m_param3":"","m_param4":"","m_param5":""}],"m_actions":[{"m_actionType":30800,"m_delay":0.0,"m_param1":"NPC1","m_param2":"rest_idle_2","m_param3":"-1","m_param4":"15","m_param5":""}],"m_showMonitor":true}]}],"m_overalEventList":[]}