{"fileKey":"female_face_baseB_02","describe":"萝莉脸2","skinData":{"skinUnits":[{"key":"_lip","texStyle":0,"colorStyle":11,"h":320,"s":1.2000000476837159,"v":1.2000000476837159},{"key":"_eyes_pupil","texStyle":6,"colorStyle":0,"h":297,"s":2.709632396697998,"v":0.712335467338562},{"key":"_eyes_liner","texStyle":0,"colorStyle":0,"h":0,"s":1.0,"v":1.0},{"key":"_eyes_shadow","texStyle":7,"colorStyle":0,"h":0,"s":1.0,"v":1.0},{"key":"_brow","texStyle":8,"colorStyle":0,"h":0,"s":1.0,"v":1.0},{"key":"_blusher","texStyle":5,"colorStyle":0,"h":0,"s":1.20622980594635,"v":1.0},{"key":"_tattoo","texStyle":1,"colorStyle":0,"h":0,"s":1.0,"v":1.0}]},"shapeData":{"partUnits":[{"key":"felman_face.brow_width","value":0.0},{"key":"felman_face.brow_narrow","value":5.000448226928711},{"key":"felman_face.brow_up","value":0.0},{"key":"felman_face.brow_down","value":19.98802375793457},{"key":"felman_face.eyes_width","value":70.55860900878906},{"key":"felman_face.eyes_narrow","value":0.0},{"key":"felman_face.eyes_up","value":23.000789642333986},{"key":"felman_face.eyes_down","value":0.0},{"key":"felman_face.eyes_fore","value":1.390528678894043},{"key":"felman_face.eyes_back","value":0.0},{"key":"felman_face.lash_long","value":69.08827209472656},{"key":"felman_face.eyes_pupil_big","value":75.53237915039063},{"key":"felman_face.eyes_pupil_small","value":0.0},{"key":"felman_face.eyes_upper_width","value":69.95269775390625},{"key":"felman_face.eyes_upper_narrow","value":0.0},{"key":"felman_face.eyes_upper_up","value":0.04967451095581055},{"key":"felman_face.eyes_upper_down","value":0.0},{"key":"felman_face.eyes_lower_width","value":7.072978973388672},{"key":"felman_face.eyes_lower_narrow","value":0.0},{"key":"felman_face.eyes_lower_up","value":0.0},{"key":"felman_face.eyes_lower_down","value":15.516578674316407},{"key":"felman_face.eyes_ch_width","value":40.92624282836914},{"key":"felman_face.eyes_ch_narrow","value":0.0},{"key":"felman_face.eyes_ch_up","value":0.8165121078491211},{"key":"felman_face.eyes_ch_down","value":0.0},{"key":"felman_face.eyes_lh_width","value":0.0},{"key":"felman_face.eyes_lh_narrow","value":18.255115509033204},{"key":"felman_face.eyes_lh_up","value":4.107666015625},{"key":"felman_face.eyes_lh_down","value":0.0},{"key":"felman_face.nose_width","value":20.05392837524414},{"key":"felman_face.nose_narrow","value":0.0},{"key":"felman_face.nose_up","value":0.0},{"key":"felman_face.nose_dowm","value":1.0651588439941407},{"key":"felman_face.nose_fore","value":0.0},{"key":"felman_face.nose_back","value":1.0651588439941407},{"key":"felman_face.nose_bridge_width","value":0.0},{"key":"felman_face.nose_bridge_narrow","value":1.5563130378723145},{"key":"felman_face.nose_bridge_high","value":51.53091812133789},{"key":"felman_face.nose_bridge_low","value":0.0},{"key":"felman_face.nose_guard_width","value":26.847034454345704},{"key":"felman_face.nose_guard_narrow","value":0.0},{"key":"felman_face.nose_guard_high","value":0.27421116828918459},{"key":"felman_face.nose_guard_low","value":0.0},{"key":"felman_face.nose_guard_long","value":23.937034606933595},{"key":"felman_face.nose_guard_short","value":0.0},{"key":"felman_face.nose_wing_width","value":15.142524719238282},{"key":"felman_face.nose_wing_narrow","value":0.0},{"key":"felman_face.nose_wing_up","value":53.942691802978519},{"key":"felman_face.nose_wing_down","value":0.0},{"key":"felman_face.nose_base_width","value":0.4082798957824707},{"key":"felman_face.nose_base_narrow","value":0.0},{"key":"felman_face.nose_base_up","value":0.0},{"key":"felman_face.nose_base_down","value":2.538585662841797},{"key":"felman_face.lip_width","value":0.0},{"key":"felman_face.lip_narrow","value":19.88756561279297},{"key":"felman_face.lip_up","value":0.0},{"key":"felman_face.lip_down","value":0.0828862190246582},{"key":"felman_face.lip_fore","value":4.254502296447754},{"key":"felman_face.lip_back","value":0.0},{"key":"felman_face.lip_upper_thick","value":73.62712097167969},{"key":"felman_face.lip_upper_thin","value":0.0},{"key":"felman_face.lip_lower_thick","value":16.203916549682618},{"key":"felman_face.lip_lower_thin","value":0.0},{"key":"felman_face.lip_angle_width","value":82.65325927734375},{"key":"felman_face.lip_angle_narrow","value":0.0},{"key":"felman_face.lip_angle_up","value":0.0},{"key":"felman_face.lip_angle_down","value":17.74553108215332},{"key":"felman_face.forehead_fore","value":6.2626543045043949},{"key":"felman_face.forehead_back","value":0.0},{"key":"felman_face.zygoma_width","value":0.0},{"key":"felman_face.zygoma_narrow","value":17.7274227142334},{"key":"felman_face.zygoma_up","value":14.077335357666016},{"key":"felman_face.zygoma_down","value":0.0},{"key":"felman_face.zygoma_fore","value":0.0},{"key":"felman_face.zygoma_back","value":0.0},{"key":"felman_face.applezone_width","value":1.045447587966919},{"key":"felman_face.applezone_narrow","value":0.0},{"key":"felman_face.applezone_up","value":0.0},{"key":"felman_face.applezone_down","value":50.695072174072269},{"key":"felman_face.applezone_fore","value":0.0},{"key":"felman_face.applezone_back","value":55.3833122253418},{"key":"felman_face.cheek_width","value":19.847511291503908},{"key":"felman_face.cheek_narrow","value":0.0},{"key":"felman_face.cheek_up","value":0.8671820163726807},{"key":"felman_face.cheek_down","value":0.0},{"key":"felman_face.jaw_width","value":0.0},{"key":"felman_face.jaw_narrow","value":26.362037658691408},{"key":"felman_face.jaw_up","value":0.0},{"key":"felman_face.jaw_down","value":16.45630645751953},{"key":"felman_face.jaw_fore","value":0.0},{"key":"felman_face.jaw_back","value":16.864585876464845},{"key":"felman_face.underjaw_width","value":45.26176452636719},{"key":"felman_face.underjaw_narrow","value":0.0},{"key":"felman_face.underjaw_up","value":27.829307556152345},{"key":"felman_face.underjaw_down","value":0.0},{"key":"felman_face.mandible_width","value":14.651351928710938},{"key":"felman_face.mandible_narrow","value":0.0}]}}